{
  "profileType" : "EXPENSIVE_SEEKER",
  "userName" : "Eve Wilson",
  "userEmail" : "eve.wilson@email.com",
  "userAge" : 24,
  "profileCreatedAt" : "2025-12-19 19:10:40",
  "lastActivityAt" : "2025-12-19 19:10:42",
  "totalOperations" : 35,
  "operationHistory" : [ {
    "operationName" : "getAllProducts",
    "operationType" : "READ",
    "timestamp" : "2025-12-19 19:10:40",
    "userName" : "Eve Wilson",
    "userEmail" : "eve.wilson@email.com",
    "productId" : null,
    "productName" : null,
    "productPrice" : null,
    "additionalInfo" : null
  }, {
    "operationName" : "getAllProducts",
    "operationType" : "READ",
    "timestamp" : "2025-12-19 19:10:40",
    "userName" : "Eve Wilson",
    "userEmail" : "eve.wilson@email.com",
    "productId" : null,
    "productName" : null,
    "productPrice" : null,
    "additionalInfo" : null
  }, {
    "operationName" : "getAllProducts",
    "operationType" : "READ",
    "timestamp" : "2025-12-19 19:10:40",
    "userName" : "Eve Wilson",
    "userEmail" : "eve.wilson@email.com",
    "productId" : null,
    "productName" : null,
    "productPrice" : null,
    "additionalInfo" : null
  }, {
    "operationName" : "getAllProducts",
    "operationType" : "READ",
    "timestamp" : "2025-12-19 19:10:40",
    "userName" : "Eve Wilson",
    "userEmail" : "eve.wilson@email.com",
    "productId" : null,
    "productName" : null,
    "productPrice" : null,
    "additionalInfo" : null
  }, {
    "operationName" : "getAllProducts",
    "operationType" : "READ",
    "timestamp" : "2025-12-19 19:10:40",
    "userName" : "Eve Wilson",
    "userEmail" : "eve.wilson@email.com",
    "productId" : null,
    "productName" : null,
    "productPrice" : null,
    "additionalInfo" : null
  }, {
    "operationName" : "getAllProducts",
    "operationType" : "READ",
    "timestamp" : "2025-12-19 19:10:40",
    "userName" : "Eve Wilson",
    "userEmail" : "eve.wilson@email.com",
    "productId" : null,
    "productName" : null,
    "productPrice" : null,
    "additionalInfo" : null
  }, {
    "operationName" : "getProductById",
    "operationType" : "READ",
    "timestamp" : "2025-12-19 19:10:41",
    "userName" : "Eve Wilson",
    "userEmail" : "eve.wilson@email.com",
    "productId" : 7,
    "productName" : "Mechanical Keyboard",
    "productPrice" : 79.99,
    "additionalInfo" : null
  }, {
    "operationName" : "getProductById",
    "operationType" : "READ",
    "timestamp" : "2025-12-19 19:10:41",
    "userName" : "Eve Wilson",
    "userEmail" : "eve.wilson@email.com",
    "productId" : 8,
    "productName" : "Webcam HD",
    "productPrice" : 89.99,
    "additionalInfo" : null
  }, {
    "operationName" : "getProductById",
    "operationType" : "READ",
    "timestamp" : "2025-12-19 19:10:41",
    "userName" : "Eve Wilson",
    "userEmail" : "eve.wilson@email.com",
    "productId" : 12,
    "productName" : "Mechanical Keyboard RGB",
    "productPrice" : 149.99,
    "additionalInfo" : null
  }, {
    "operationName" : "viewExpensiveProduct",
    "operationType" : "SEARCH_EXPENSIVE",
    "timestamp" : "2025-12-19 19:10:41",
    "userName" : "Eve Wilson",
    "userEmail" : "eve.wilson@email.com",
    "productId" : 12,
    "productName" : "Mechanical Keyboard RGB",
    "productPrice" : 149.99,
    "additionalInfo" : null
  }, {
    "operationName" : "getProductById",
    "operationType" : "READ",
    "timestamp" : "2025-12-19 19:10:41",
    "userName" : "Eve Wilson",
    "userEmail" : "eve.wilson@email.com",
    "productId" : 13,
    "productName" : "Noise Cancelling Headphones",
    "productPrice" : 349.99,
    "additionalInfo" : null
  }, {
    "operationName" : "viewExpensiveProduct",
    "operationType" : "SEARCH_EXPENSIVE",
    "timestamp" : "2025-12-19 19:10:41",
    "userName" : "Eve Wilson",
    "userEmail" : "eve.wilson@email.com",
    "productId" : 13,
    "productName" : "Noise Cancelling Headphones",
    "productPrice" : 349.99,
    "additionalInfo" : null
  }, {
    "operationName" : "getProductById",
    "operationType" : "READ",
    "timestamp" : "2025-12-19 19:10:41",
    "userName" : "Eve Wilson",
    "userEmail" : "eve.wilson@email.com",
    "productId" : 15,
    "productName" : "MacBook Air M3",
    "productPrice" : 1299.99,
    "additionalInfo" : null
  }, {
    "operationName" : "viewExpensiveProduct",
    "operationType" : "SEARCH_EXPENSIVE",
    "timestamp" : "2025-12-19 19:10:41",
    "userName" : "Eve Wilson",
    "userEmail" : "eve.wilson@email.com",
    "productId" : 15,
    "productName" : "MacBook Air M3",
    "productPrice" : 1299.99,
    "additionalInfo" : null
  }, {
    "operationName" : "getProductById",
    "operationType" : "READ",
    "timestamp" : "2025-12-19 19:10:41",
    "userName" : "Eve Wilson",
    "userEmail" : "eve.wilson@email.com",
    "productId" : 7,
    "productName" : "Mechanical Keyboard",
    "productPrice" : 79.99,
    "additionalInfo" : null
  }, {
    "operationName" : "getProductById",
    "operationType" : "READ",
    "timestamp" : "2025-12-19 19:10:41",
    "userName" : "Eve Wilson",
    "userEmail" : "eve.wilson@email.com",
    "productId" : 8,
    "productName" : "Webcam HD",
    "productPrice" : 89.99,
    "additionalInfo" : null
  }, {
    "operationName" : "getProductById",
    "operationType" : "READ",
    "timestamp" : "2025-12-19 19:10:41",
    "userName" : "Eve Wilson",
    "userEmail" : "eve.wilson@email.com",
    "productId" : 12,
    "productName" : "Mechanical Keyboard RGB",
    "productPrice" : 149.99,
    "additionalInfo" : null
  }, {
    "operationName" : "viewExpensiveProduct",
    "operationType" : "SEARCH_EXPENSIVE",
    "timestamp" : "2025-12-19 19:10:41",
    "userName" : "Eve Wilson",
    "userEmail" : "eve.wilson@email.com",
    "productId" : 12,
    "productName" : "Mechanical Keyboard RGB",
    "productPrice" : 149.99,
    "additionalInfo" : null
  }, {
    "operationName" : "getProductById",
    "operationType" : "READ",
    "timestamp" : "2025-12-19 19:10:41",
    "userName" : "Eve Wilson",
    "userEmail" : "eve.wilson@email.com",
    "productId" : 13,
    "productName" : "Noise Cancelling Headphones",
    "productPrice" : 349.99,
    "additionalInfo" : null
  }, {
    "operationName" : "viewExpensiveProduct",
    "operationType" : "SEARCH_EXPENSIVE",
    "timestamp" : "2025-12-19 19:10:41",
    "userName" : "Eve Wilson",
    "userEmail" : "eve.wilson@email.com",
    "productId" : 13,
    "productName" : "Noise Cancelling Headphones",
    "productPrice" : 349.99,
    "additionalInfo" : null
  }, {
    "operationName" : "getProductById",
    "operationType" : "READ",
    "timestamp" : "2025-12-19 19:10:41",
    "userName" : "Eve Wilson",
    "userEmail" : "eve.wilson@email.com",
    "productId" : 15,
    "productName" : "MacBook Air M3",
    "productPrice" : 1299.99,
    "additionalInfo" : null
  }, {
    "operationName" : "viewExpensiveProduct",
    "operationType" : "SEARCH_EXPENSIVE",
    "timestamp" : "2025-12-19 19:10:41",
    "userName" : "Eve Wilson",
    "userEmail" : "eve.wilson@email.com",
    "productId" : 15,
    "productName" : "MacBook Air M3",
    "productPrice" : 1299.99,
    "additionalInfo" : null
  }, {
    "operationName" : "getProductById",
    "operationType" : "READ",
    "timestamp" : "2025-12-19 19:10:41",
    "userName" : "Eve Wilson",
    "userEmail" : "eve.wilson@email.com",
    "productId" : 7,
    "productName" : "Mechanical Keyboard",
    "productPrice" : 79.99,
    "additionalInfo" : null
  }, {
    "operationName" : "getProductById",
    "operationType" : "READ",
    "timestamp" : "2025-12-19 19:10:41",
    "userName" : "Eve Wilson",
    "userEmail" : "eve.wilson@email.com",
    "productId" : 8,
    "productName" : "Webcam HD",
    "productPrice" : 89.99,
    "additionalInfo" : null
  }, {
    "operationName" : "getProductById",
    "operationType" : "READ",
    "timestamp" : "2025-12-19 19:10:41",
    "userName" : "Eve Wilson",
    "userEmail" : "eve.wilson@email.com",
    "productId" : 12,
    "productName" : "Mechanical Keyboard RGB",
    "productPrice" : 149.99,
    "additionalInfo" : null
  }, {
    "operationName" : "viewExpensiveProduct",
    "operationType" : "SEARCH_EXPENSIVE",
    "timestamp" : "2025-12-19 19:10:41",
    "userName" : "Eve Wilson",
    "userEmail" : "eve.wilson@email.com",
    "productId" : 12,
    "productName" : "Mechanical Keyboard RGB",
    "productPrice" : 149.99,
    "additionalInfo" : null
  }, {
    "operationName" : "getProductById",
    "operationType" : "READ",
    "timestamp" : "2025-12-19 19:10:41",
    "userName" : "Eve Wilson",
    "userEmail" : "eve.wilson@email.com",
    "productId" : 13,
    "productName" : "Noise Cancelling Headphones",
    "productPrice" : 349.99,
    "additionalInfo" : null
  }, {
    "operationName" : "viewExpensiveProduct",
    "operationType" : "SEARCH_EXPENSIVE",
    "timestamp" : "2025-12-19 19:10:41",
    "userName" : "Eve Wilson",
    "userEmail" : "eve.wilson@email.com",
    "productId" : 13,
    "productName" : "Noise Cancelling Headphones",
    "productPrice" : 349.99,
    "additionalInfo" : null
  }, {
    "operationName" : "getProductById",
    "operationType" : "READ",
    "timestamp" : "2025-12-19 19:10:41",
    "userName" : "Eve Wilson",
    "userEmail" : "eve.wilson@email.com",
    "productId" : 15,
    "productName" : "MacBook Air M3",
    "productPrice" : 1299.99,
    "additionalInfo" : null
  }, {
    "operationName" : "viewExpensiveProduct",
    "operationType" : "SEARCH_EXPENSIVE",
    "timestamp" : "2025-12-19 19:10:41",
    "userName" : "Eve Wilson",
    "userEmail" : "eve.wilson@email.com",
    "productId" : 15,
    "productName" : "MacBook Air M3",
    "productPrice" : 1299.99,
    "additionalInfo" : null
  }, {
    "operationName" : "getProductById",
    "operationType" : "READ",
    "timestamp" : "2025-12-19 19:10:42",
    "userName" : "Eve Wilson",
    "userEmail" : "eve.wilson@email.com",
    "productId" : 11,
    "productName" : "Gaming Monitor",
    "productPrice" : 299.99,
    "additionalInfo" : null
  }, {
    "operationName" : "viewExpensiveProduct",
    "operationType" : "SEARCH_EXPENSIVE",
    "timestamp" : "2025-12-19 19:10:42",
    "userName" : "Eve Wilson",
    "userEmail" : "eve.wilson@email.com",
    "productId" : 11,
    "productName" : "Gaming Monitor",
    "productPrice" : 299.99,
    "additionalInfo" : null
  }, {
    "operationName" : "getProductById",
    "operationType" : "READ",
    "timestamp" : "2025-12-19 19:10:42",
    "userName" : "Eve Wilson",
    "userEmail" : "eve.wilson@email.com",
    "productId" : 14,
    "productName" : "iPad Pro",
    "productPrice" : 899.99,
    "additionalInfo" : null
  }, {
    "operationName" : "viewExpensiveProduct",
    "operationType" : "SEARCH_EXPENSIVE",
    "timestamp" : "2025-12-19 19:10:42",
    "userName" : "Eve Wilson",
    "userEmail" : "eve.wilson@email.com",
    "productId" : 14,
    "productName" : "iPad Pro",
    "productPrice" : 899.99,
    "additionalInfo" : null
  }, {
    "operationName" : "getProductById",
    "operationType" : "READ",
    "timestamp" : "2025-12-19 19:10:42",
    "userName" : "Eve Wilson",
    "userEmail" : "eve.wilson@email.com",
    "productId" : 19,
    "productName" : "LG OLED TV 77\"",
    "productPrice" : 2999.99,
    "additionalInfo" : null
  }, {
    "operationName" : "viewExpensiveProduct",
    "operationType" : "SEARCH_EXPENSIVE",
    "timestamp" : "2025-12-19 19:10:42",
    "userName" : "Eve Wilson",
    "userEmail" : "eve.wilson@email.com",
    "productId" : 19,
    "productName" : "LG OLED TV 77\"",
    "productPrice" : 2999.99,
    "additionalInfo" : null
  }, {
    "operationName" : "getProductById",
    "operationType" : "READ",
    "timestamp" : "2025-12-19 19:10:42",
    "userName" : "Eve Wilson",
    "userEmail" : "eve.wilson@email.com",
    "productId" : 20,
    "productName" : "Gaming Laptop RTX 4090",
    "productPrice" : 3499.99,
    "additionalInfo" : null
  }, {
    "operationName" : "viewExpensiveProduct",
    "operationType" : "SEARCH_EXPENSIVE",
    "timestamp" : "2025-12-19 19:10:42",
    "userName" : "Eve Wilson",
    "userEmail" : "eve.wilson@email.com",
    "productId" : 20,
    "productName" : "Gaming Laptop RTX 4090",
    "productPrice" : 3499.99,
    "additionalInfo" : null
  }, {
    "operationName" : "getProductById",
    "operationType" : "READ",
    "timestamp" : "2025-12-19 19:10:42",
    "userName" : "Eve Wilson",
    "userEmail" : "eve.wilson@email.com",
    "productId" : 2,
    "productName" : "Mouse Pad",
    "productPrice" : 14.99,
    "additionalInfo" : null
  }, {
    "operationName" : "getProductById",
    "operationType" : "READ",
    "timestamp" : "2025-12-19 19:10:42",
    "userName" : "Eve Wilson",
    "userEmail" : "eve.wilson@email.com",
    "productId" : 7,
    "productName" : "Mechanical Keyboard",
    "productPrice" : 79.99,
    "additionalInfo" : null
  }, {
    "operationName" : "getProductById",
    "operationType" : "READ",
    "timestamp" : "2025-12-19 19:10:42",
    "userName" : "Eve Wilson",
    "userEmail" : "eve.wilson@email.com",
    "productId" : 9,
    "productName" : "Desk Lamp",
    "productPrice" : 69.99,
    "additionalInfo" : null
  } ],
  "expensiveProductViews" : 26,
  "totalProductViews" : 35,
  "expensiveProductViewPercentage" : 74.28571428571429,
  "averagePriceViewed" : 767.8471428571428,
  "highestPriceViewed" : 3499.99,
  "lowestPriceViewed" : 14.99,
  "expensiveProducts" : [ {
    "productId" : 12,
    "productName" : "Mechanical Keyboard RGB",
    "price" : 149.99,
    "viewCount" : 6
  }, {
    "productId" : 13,
    "productName" : "Noise Cancelling Headphones",
    "price" : 349.99,
    "viewCount" : 6
  }, {
    "productId" : 15,
    "productName" : "MacBook Air M3",
    "price" : 1299.99,
    "viewCount" : 6
  }, {
    "productId" : 11,
    "productName" : "Gaming Monitor",
    "price" : 299.99,
    "viewCount" : 2
  }, {
    "productId" : 14,
    "productName" : "iPad Pro",
    "price" : 899.99,
    "viewCount" : 2
  }, {
    "productId" : 19,
    "productName" : "LG OLED TV 77\"",
    "price" : 2999.99,
    "viewCount" : 2
  }, {
    "productId" : 20,
    "productName" : "Gaming Laptop RTX 4090",
    "price" : 3499.99,
    "viewCount" : 2
  } ],
  "profileDescription" : "User interested in expensive products (74,3% of views > €100,00)",
  "profileType" : "EXPENSIVE_SEEKER"
}